Workbook

Sheet Estoque de Produtos
A1: Código | B1: Produto | C1: Categoria | D1: Custo (R$) | E1: Preço Venda (R$) | F1: Margem (%) | G1: Estoque Atual | H1: Tamanhos | I1: Valor Total (R$) | J1: Status
A2: PRD001 | B2: Camiseta Básica Branca | C2: Camisetas | D2: 45.9 | E2: 89.9 | F2: =((E2-D2)/D2)*100 | G2: 156 | H2: P/M/G/GG | I2: =D2*G2 | J2: =SE(G2<50;"Baixo";SE(G2<100;"Médio";"Alto"))
A3: PRD002 | B3: Calça Jeans Skinny | C3: Calças | D3: 89.5 | E3: 179.9 | F3: =((E3-D3)/D3)*100 | G3: 87 | H3: 36-44 | I3: =D3*G3 | J3: =SE(G3<50;"Baixo";SE(G3<100;"Médio";"Alto"))
A4: PRD003 | B4: Vestido Floral Verão | C4: Vestidos | D4: 72.3 | E4: 159.9 | F4: =((E4-D4)/D4)*100 | G4: 64 | H4: P/M/G | I4: =D4*G4 | J4: =SE(G4<50;"Baixo";SE(G4<100;"Médio";"Alto"))
A5: PRD004 | B5: Blazer Executivo Preto | C5: Blazers | D5: 125 | E5: 289.9 | F5: =((E5-D5)/D5)*100 | G5: 43 | H5: P/M/G/GG | I5: =D5*G5 | J5: =SE(G5<50;"Baixo";SE(G5<100;"Médio";"Alto"))
A6: PRD005 | B6: Short Jeans Destroyed | C6: Shorts | D6: 58.4 | E6: 119.9 | F6: =((E6-D6)/D6)*100 | G6: 92 | H6: 36-44 | I6: =D6*G6 | J6: =SE(G6<50;"Baixo";SE(G6<100;"Médio";"Alto"))
A7: PRD006 | B7: Blusa Manga Longa | C7: Blusas | D7: 52.8 | E7: 109.9 | F7: =((E7-D7)/D7)*100 | G7: 118 | H7: P/M/G/GG | I7: =D7*G7 | J7: =SE(G7<50;"Baixo";SE(G7<100;"Médio";"Alto"))
A8: PRD007 | B8: Saia Midi Plissada | C8: Saias | D8: 64.2 | E8: 139.9 | F8: =((E8-D8)/D8)*100 | G8: 71 | H8: P/M/G | I8: =D8*G8 | J8: =SE(G8<50;"Baixo";SE(G8<100;"Médio";"Alto"))
A9: PRD008 | B9: Jaqueta Jeans | C9: Jaquetas | D9: 98.7 | E9: 219.9 | F9: =((E9-D9)/D9)*100 | G9: 54 | H9: P/M/G/GG | I9: =D9*G9 | J9: =SE(G9<50;"Baixo";SE(G9<100;"Médio";"Alto"))
A10: PRD009 | B10: Body Manga Curta | C10: Bodies | D10: 38.5 | E10: 79.9 | F10: =((E10-D10)/D10)*100 | G10: 134 | H10: P/M/G | I10: =D10*G10 | J10: =SE(G10<50;"Baixo";SE(G10<100;"Médio";"Alto"))
A11: PRD010 | B11: Calça Alfaiataria | C11: Calças | D11: 95.3 | E11: 199.9 | F11: =((E11-D11)/D11)*100 | G11: 59 | H11: 36-44 | I11: =D11*G11 | J11: =SE(G11<50;"Baixo";SE(G11<100;"Médio";"Alto"))
A12: PRD011 | B12: Camiseta Estampada | C12: Camisetas | D12: 49.9 | E12: 99.9 | F12: =((E12-D12)/D12)*100 | G12: 143 | H12: P/M/G/GG | I12: =D12*G12 | J12: =SE(G12<50;"Baixo";SE(G12<100;"Médio";"Alto"))
A13: PRD012 | B13: Vestido Longo Festa | C13: Vestidos | D13: 145 | E13: 329.9 | F13: =((E13-D13)/D13)*100 | G13: 28 | H13: P/M/G | I13: =D13*G13 | J13: =SE(G13<50;"Baixo";SE(G13<100;"Médio";"Alto"))
... A21: PRD020 | B21: Kimono Estampado | C21: Kimonos | D21: 82.5 | E21: 179.9 | F21: =((E21-D21)/D21)*100 | G21: 38 | H21: Único | I21: =D21*G21 | J21: =SE(G21<50;"Baixo";SE(G21<100;"Médio";"Alto"))
B22: TOTAL GERAL | I22: =SOMA(I2:I21)

Sheet Vendas Diárias
A1: Data | B1: Nº Venda | C1: Código Produto | D1: Produto | E1: Quantidade | F1: Preço Unit. (R$) | G1: Desconto (%) | H1: Total (R$) | I1: Forma Pagamento | J1: Vendedor
A2: 45986.612 | B2: VND1200 | C2: PRD008 | D2: Jaqueta Jeans | E2: 3 | F2: 219.9 | G2: 0.15 | H2: =E2*F2*(1-G2) | I2: Crédito 2x | J2: Mariana Costa
A3: 45987.612 | B3: VND1201 | C3: PRD004 | D3: Blazer Executivo Preto | E3: 1 | F3: 289.9 | G3: 0 | H3: =E3*F3*(1-G3) | I3: Crédito à Vista | J3: Roberto Lima
A4: 45988.612 | B4: VND1202 | C4: PRD011 | D4: Camiseta Estampada | E4: 2 | F4: 99.9 | G4: 0 | H4: =E4*F4*(1-G4) | I4: Crédito à Vista | J4: Carlos Santos
A5: 45989.612 | B5: VND1203 | C5: PRD012 | D5: Vestido Longo Festa | E5: 4 | F5: 329.9 | G5: 0.15 | H5: =E5*F5*(1-G5) | I5: Crédito 2x | J5: Mariana Costa
A6: 45990.612 | B6: VND1204 | C6: PRD004 | D6: Blazer Executivo Preto | E6: 5 | F6: 289.9 | G6: 0 | H6: =E6*F6*(1-G6) | I6: PIX | J6: Carlos Santos
A7: 45991.612 | B7: VND1205 | C7: PRD005 | D7: Short Jeans Destroyed | E7: 1 | F7: 119.9 | G7: 0.15 | H7: =E7*F7*(1-G7) | I7: Crédito 2x | J7: Juliana Oliveira
A8: 45992.612 | B8: VND1206 | C8: PRD018 | D8: Conjunto Moletom | E8: 3 | F8: 249.9 | G8: 0 | H8: =E8*F8*(1-G8) | I8: Crédito 2x | J8: Carlos Santos
A9: 45993.612 | B9: VND1207 | C9: PRD009 | D9: Body Manga Curta | E9: 4 | F9: 79.9 | G9: 0.05 | H9: =E9*F9*(1-G9) | I9: Crédito à Vista | J9: Roberto Lima
A10: 45994.612 | B10: VND1208 | C10: PRD012 | D10: Vestido Longo Festa | E10: 5 | F10: 329.9 | G10: 0 | H10: =E10*F10*(1-G10) | I10: Dinheiro | J10: Roberto Lima
A11: 45995.612 | B11: VND1209 | C11: PRD010 | D11: Calça Alfaiataria | E11: 3 | F11: 199.9 | G11: 0 | H11: =E11*F11*(1-G11) | I11: Crédito à Vista | J11: Ana Silva
A12: 45996.612 | B12: VND1210 | C12: PRD017 | D12: Camisa Social Branca | E12: 1 | F12: 149.9 | G12: 0.05 | H12: =E12*F12*(1-G12) | I12: Crédito à Vista | J12: Roberto Lima
A13: 45997.612 | B13: VND1211 | C13: PRD019 | D13: Legging Fitness | E13: 3 | F13: 99.9 | G13: 0 | H13: =E13*F13*(1-G13) | I13: Crédito 2x | J13: Mariana Costa
... A26: 46010.612 | B26: VND1224 | C26: PRD008 | D26: Jaqueta Jeans | E26: 5 | F26: 219.9 | G26: 0.05 | H26: =E26*F26*(1-G26) | I26: Crédito 3x | J26: Mariana Costa
D27: TOTAL DE VENDAS | H27: =SOMA(H2:H26)

Sheet Dashboard
A1: DASHBOARD - LOJA DE ROUPAS
A3: Indicador | B3: Valor | C3: Meta | D3: Status
A4: Total em Estoque (R$) | B4: =SOMA('Estoque de Produtos'!I2:I21) | C4: 150000 | D4: =SE(B4>=C4;"✓";"⚠")
A5: Total de Vendas (R$) | B5: =SOMA('Vendas Diárias'!H2:H26) | C5: 50000 | D5: =SE(B5>=C5;"✓";"⚠")
A6: Ticket Médio (R$) | B6: =MÉDIA('Vendas Diárias'!H2:H26) | C6: 300 | D6: =SE(B6>=C6;"✓";"⚠")
A7: Produtos em Estoque | B7: =CONT.VALORES('Estoque de Produtos'!A2:A21) | C7: 20 | D7: =SE(B7>=C7;"✓";"⚠")
A8: Total de Vendas | B8: =CONT.VALORES('Vendas Diárias'!B2:B26) | C8: 30 | D8: =SE(B8>=C8;"✓";"⚠")
A11: Categoria | B11: Quantidade
A12: Blazers | B12: 43
A13: Blusas | B13: 118
A14: Bodies | B14: 134
A15: Calças | B15: 146
A16: Camisas | B16: 96
A17: Camisetas | B17: 299
A18: Casacos | B18: 67
A19: Conjuntos | B19: 52
A20: Fitness | B20: 124
A21: Jaquetas | B21: 54
A22: Kimonos | B22: 38
A23: Macacões | B23: 45
... A27: Vestidos | B27: 92
